{"stats":{"minecraft:custom":{"minecraft:time_since_rest":13178,"minecraft:walk_one_cm":4700,"minecraft:leave_game":2,"minecraft:mob_kills":1,"minecraft:damage_taken":518,"minecraft:play_time":27853,"minecraft:damage_dealt":221,"minecraft:jump":40,"minecraft:time_since_death":6963,"minecraft:sprint_one_cm":1904,"minecraft:fall_one_cm":325,"minecraft:total_world_time":27853,"minecraft:fly_one_cm":2267,"minecraft:deaths":2},"minecraft:used":{"minecraft:stone_axe":4},"minecraft:killed_by":{"minecraft:player":1,"minecraft:zombie":1},"minecraft:killed":{"minecraft:zombie":1}},"DataVersion":4440}